setup.py
NYPL/__init__.py
NYPL/api.py
NYPL/example.py
NYPL.egg-info/PKG-INFO
NYPL.egg-info/SOURCES.txt
NYPL.egg-info/dependency_links.txt
NYPL.egg-info/requires.txt
NYPL.egg-info/top_level.txt