Metadata-Version: 1.0
Name: NYPL
Version: 0.1.9
Summary: An unoffical API for the New York Public Library
Home-page: https://github.com/susinmotion/NYPL
Author: Susan Steinman
Author-email: steinman.tutoring@gmail.com
License: UNKNOWN
Platform: UNKNOWN
